Experiencia05/VHDL/serial_out.vhd
-------------------------------------------------------------------------------
-- Author: Kauê Rodrigues Barbosa (kaue.rodrigueskrb@usp.br)
-- Module Name: serial_out
-- Description:
-- Sends 8 bits via serial port to a computer
-------------------------------------------------------------------------------

library IEEE;
use IEEE.numeric_bit.all;

entity serial_out is
    generic( 
        POLARITY  : boolean := TRUE;
        WIDTH     : natural := 7;
        PARITY    : natural := 1;
        STOP_BITS : natural := 1
    );

    port( 
        clock, reset, tx_go  : in  bit;
        tx_done              : out  bit;
        data                 : in bit_vector(WIDTH-1 downto 0);    
        serial_o : out  bit
    );
end serial_out;

architecture arch_serial of serial_out is
    signal done, rst                          : bit := '0';
    signal intern                             : bit_vector(WIDTH-1 downto 0);
    signal start_bit, serial_intern, stop_bit : bit := '0';
    signal count, stop_count: natural := 0;

    type estados is (ready, send_data_true, send_data_false, send_parity_bit_odd,
                     send_parity_bit_even, send_stop_true, send_stop_false);
    signal estado : estados := ready;
begin
    
    -- Verificação da polariadade
    --start_bit <= '0' when POLARITY = TRUE else '1';
    --intern    <= data when POLARITY = TRUE else not data;
    --stop_bit  <= '1' when POLARITY = TRUE else '0';

    intern <= data;
    rst <= reset;

    TRANSMISSION:
    process(clock, reset, tx_go)
        variable paridade : bit := '0';
    begin
        if rising_edge(clock) then
            case (estado) is 
                when ready =>
                    if rst = '1' then
                        serial_intern <= '1'; --Verificar depois
                        estado <= ready;
                    end if;

                    if POLARITY = TRUE then
                        serial_intern <= '1';
                    elsif POLARITY = FALSE then
                        serial_intern <= '0';
                    end if;

                    if tx_go = '0' then
                        estado <= ready;
                    elsif tx_go = '1' then
                        done <= '0';
                        if POLARITY = TRUE then
                            serial_intern <= '0';
                            estado <= send_data_true;
                        elsif POLARITY = FALSE then
                            serial_intern <= '1';
                            estado <= send_data_false;
                        end if;
                    end if;

                when send_data_true =>
                    if rst = '1' then
                        serial_intern <= '1';
                        count <= 0;
                        estado <= ready;
                    end if;

                    serial_intern <= intern(count);
                    count <= count + 1;
                    if count < WIDTH-1 then 
                        estado <= send_data_true;
                    elsif PARITY = 1 then
                        count <= 0;
                        estado <= send_parity_bit_odd;
                    elsif PARITY = 0 then
                        count <= 0;
                        estado <= send_parity_bit_even;
                    end if;
                
                when send_data_false => 
                    if rst = '1' then
                        serial_intern <= '0';
                        count <= 0;
                        estado <= ready;
                    end if;

                    serial_intern <= not intern(count);
                    count <= count + 1;
                    if count < WIDTH-1 then 
                        estado <= send_data_false;
                    elsif PARITY = 1 then
                        count <= 0;
                        estado <= send_parity_bit_odd;
                    elsif PARITY = 0 then
                        count <= 0;
                        estado <= send_parity_bit_even;
                    end if;

                when send_parity_bit_odd =>
                    if rst = '1' then
                        serial_intern <= '1'; -- Verificar true e false
                        count <= 0;
                        estado <= ready;
                    end if;

                    for i in intern'range loop
                        paridade := paridade xor intern(i);
                    end loop;

                    serial_intern <= not paridade;
                    estado <= send_stop_true;
                    
                
                when send_parity_bit_even =>
                    if rst = '1' then
                        serial_intern <= '1'; -- Verificar true e false
                        count <= 0;
                        estado <= ready;
                    end if;

                    for i in intern'range loop
                        paridade := paridade xor intern(i);
                    end loop;

                    serial_intern <= paridade;   
                    estado <= send_stop_true;
               
                
                when send_stop_true =>
                    if rst = '1' then
                        serial_intern <= '1'; -- Verificar true e false
                        count <= 0;
                        estado <= ready;
                    end if;

                    paridade := '0';
                    serial_intern <= '1';
                    stop_count <= stop_count + 1;
                    if stop_count < STOP_BITS-1 then
                        estado <= send_stop_true;
                    else 
                        stop_count <= 0;
                        done <= '1';
                        estado <= ready;
                    end if;

                when send_stop_false =>
                    if rst = '1' then
                        serial_intern <= '0'; -- Verificar true e false
                        count <= 0;
                        estado <= ready;
                    end if;

                    paridade := '0';
                    serial_intern <= '0';
                    stop_count <= stop_count + 1;
                    if stop_count < STOP_BITS-1 then
                        estado <= send_stop_true;
                    else 
                        stop_count <= 0;
                        done <= '1';
                        estado <= ready;
                    end if;

            end case;
        end if;
    end process;

    serial_o <= serial_intern;
    tx_done    <= done;
end arch_serial;
--
--        if reset = '0' then
--            done <= '0';
--        elsif tx_go = '1' then
--            done <= '0';
--            if rising_edge(clock) then
--                serial_intern <= start_bit;
--
--                for i in 0 to WIDTH-1 loop
--                    serial_intern <= intern(i);
--                end loop;
--                
--                if PARITY = 1 then
--                    for i in intern'range loop
--                        paridade := paridade xor intern(i);
--                    end loop;
--                    serial_intern <= not paridade;
--                else 
--                    for i in intern'range loop
--                        paridade := paridade xor intern(i);
--                    end loop;
--                    serial_intern <= paridade;
--                end if;
--                
--                for i in 0 to STOP_BITS loop
--                    serial_intern <= stop_bit;
--                end loop;               
--            end if;
--            done <= '1';
--        end if;
--    end process;
--
--    serial_o <= serial_intern;
--    tx_done    <= done;

Experiencia05/VHDL/tx_tb.vhd
library IEEE;
use IEEE.numeric_bit.all;

entity serial_out_tb is
end serial_out_tb;

architecture behavior of serial_out_tb is 
    -- Component Declaration for the Unit Under Test (UUT)
    component serial_out
    generic (
        POLARITY  : boolean := TRUE;
        WIDTH     : natural := 8;
        PARITY    : natural := 1;
        STOP_BITS : natural := 1
    );
    port (
        clock    : in  bit;
        reset    : in  bit;
        tx_go    : in  bit;
        tx_done  : out bit;
        data     : in  bit_vector(WIDTH-1 downto 0);
        serial_o : out bit
    );
    end component;

    component serial_out2
    generic (
        POLARITY  : boolean := TRUE;
        WIDTH     : natural := 8;
        PARITY    : natural := 1;
        STOP_BITS : natural := 1
    );
    port (
        clock    : in  bit;
        reset    : in  bit;
        tx_go    : in  bit;
        tx_done  : out bit;
        data     : in  bit_vector(WIDTH-1 downto 0);
        serial_o : out bit
    );
    end component;

    --Inputs
    signal clock : bit := '0';
    signal reset : bit := '0';
    signal tx_go : bit := '0';
    signal data : bit_vector(7 downto 0);

    --Outputs
    signal tx_done  : bit;
    signal serial_o : bit;
    

    -- Control
    signal finished: bit := '0';
    constant half_period : time := 10 ns;

begin

    dut: serial_out generic map (
            POLARITY  => TRUE,
            WIDTH     => 8,
            PARITY    => 1,
            STOP_BITS => 1
        )
        port map (
            clock    => clock,
            reset    => reset,
            tx_go    => tx_go,
            tx_done  => tx_done,
            data     => data,
            serial_o => serial_o
        );

    clock <= not clock after half_period when finished /= '1' else '0';


    test: process
    begin
        report "Inicio testes";
        
        data  <= "11010101"; --Paridade 0
        reset <= '1';
        wait for 4*half_period;  
        reset <= '0'; 
        tx_go <= '1';
        wait until rising_edge(clock);

        wait until falling_edge(clock); --Amostra no meio do bit
        assert serial_o = '0'
        report "Start Bit falhou";

        tx_go <= '0';

        for i in data'reverse_range loop
            wait until falling_edge(clock);
            assert serial_o = data(i)
            report "serial:" & bit'image(serial_o) & ", esperado:" &bit'image(data(i))&"idx:"&integer'image(i);
        end loop;

        wait until falling_edge(clock);
        assert serial_o = '0'
        report "Teste Paridade Falhou";

        
        wait until falling_edge(clock);
        assert serial_o = '1'
        report "Stop Bit falhou";
        assert tx_done = '1'
        report "Done Falhou";

        report "Fim teste transmissao inicial";

        wait for 10*half_period;

        assert tx_done = '1'
        report "Done Deve se manter ligado";
        

        data  <= "11010101"; --Paridade 0
        reset <= '1';
        wait for 4*half_period;  
        
        reset <= '0'; 
        tx_go <= '1';
        wait until rising_edge(clock);

        wait until falling_edge(clock); --Amostra no meio do bit
        assert serial_o = '0'
        report "Start Bit falhou";

        for i in data'reverse_range loop
            wait until falling_edge(clock);
            assert serial_o = data(i)
            report "serial:" & bit'image(serial_o) & ", esperado:" &bit'image(data(i))&"idx:"&integer'image(i);
        end loop;

        wait until falling_edge(clock);
        assert serial_o = '0'
        report "Teste Paridade Falhou";
        wait until falling_edge(clock);
        assert serial_o = '1'
        report "Stop Bit falhou";

        report "Fim teste reset e transmissao";


        wait for 10*half_period;

        report "Inicio teste metralhadora";

        data  <= "11010101"; --Paridade 0
        reset <= '1';
        wait for 4*half_period;  
        
        reset <= '0'; 
        tx_go <= '1';
        wait until rising_edge(clock);

        for i in 0 to 2 loop
            wait until falling_edge(clock); --Amostra no meio do bit
            assert serial_o = '0'
            report "Start Bit falhou";

            if i = 2 then
                tx_go <= '0';
            end if;

            for j in data'reverse_range loop
                wait until falling_edge(clock);
                assert serial_o = data(j)
                report "serial:" & bit'image(serial_o) & ", esperado:" &bit'image(data(j))&"idx:"&integer'image(j);
            end loop;

            wait until falling_edge(clock);
            assert serial_o = '0'
            report "Teste Paridade Falhou";
            wait until falling_edge(clock);
            assert serial_o = '1'
            report "Stop Bit falhou";
        end loop;


        report "Fim teste metralhadora";


        wait for 10*half_period;

        report "Inicio teste swap data";

        data  <= "00000000"; --Paridade 1
        reset <= '1';
        wait for 4*half_period;  
        
        reset <= '0'; 
        tx_go <= '1';
        wait until rising_edge(clock);
        wait until falling_edge(clock); --Amostra no meio do bit
        assert serial_o = '0'
        report "Start Bit falhou";
        wait until falling_edge(clock); --Amostra no meio do bit
        assert serial_o = '0'
        report "1 Bit falhou";
        wait until falling_edge(clock); --Amostra no meio do bit
        assert serial_o = '0'
        report "2 Bit falhou";

        data <= "01111111"; -- Paridade 0

        wait until falling_edge(clock); --Amostra no meio do bit
        assert serial_o = '0'
        report "3 Bit falhou";
        wait until falling_edge(clock); --Amostra no meio do bit
        assert serial_o = '0'
        report "4 Bit falhou";
        wait until falling_edge(clock); --Amostra no meio do bit
        assert serial_o = '0'
        report "5 Bit falhou";
        wait until falling_edge(clock); --Amostra no meio do bit
        assert serial_o = '0'
        report "6 Bit falhou";
        wait until falling_edge(clock); --Amostra no meio do bit
        assert serial_o = '0'
        report "7 Bit falhou";
        wait until falling_edge(clock); --Amostra no meio do bit
        assert serial_o = '0'
        report "8 Bit falhou";
        wait until falling_edge(clock); --Amostra no meio do bit
        assert serial_o = '1'
        report "Paridade Falhou";
        wait until falling_edge(clock); --Amostra no meio do bit
        assert serial_o = '1'
        report "Stopbit Falhou";


        report "Fim teste swap data";

        finished <= '1';
        wait;
    end process;


end behavior;

Experiencia05/VHDL/serial_out.vcd
$date
  Fri Apr 12 12:50:39 2024
$end
$version
  GHDL v0
$end
$timescale
  1 fs
$end
$scope module standard $end
$upscope $end
$scope module numeric_bit $end
$upscope $end
$scope module serial_out_tb $end
$var reg 1 ! clock $end
$var reg 1 " reset $end
$var reg 1 # tx_go $end
$var reg 8 $ data[7:0] $end
$var reg 1 % tx_done $end
$var reg 1 & serial_o $end
$var reg 1 ' finished $end
$scope module dut $end
$var reg 1 ( clock $end
$var reg 1 ) reset $end
$var reg 1 * tx_go $end
$var reg 1 + tx_done $end
$var reg 8 , data[7:0] $end
$var reg 1 - serial_o $end
$var reg 1 . done $end
$var reg 1 / rst $end
$var reg 8 0 intern[7:0] $end
$var reg 1 1 start_bit $end
$var reg 1 2 serial_intern $end
$var reg 1 3 stop_bit $end
$var integer 32 4 count $end
$var integer 32 5 stop_count $end
$comment estado is not handled $end
$upscope $end
$upscope $end
$enddefinitions $end
#0
0!
1"
0#
b11010101 $
0%
0&
0'
0(
1)
0*
0+
b11010101 ,
0-
0.
1/
b11010101 0
01
02
03
b0 4
b0 5
#10000000
1!
1&
1(
1-
12
#20000000
0!
0(
#30000000
1!
1(
#40000000
0!
0"
1#
0(
0)
1*
0/
#50000000
1!
0&
1(
0-
02
#60000000
0!
0#
0(
0*
#70000000
1!
1&
1(
1-
12
b1 4
#80000000
0!
0(
#90000000
1!
0&
1(
0-
02
b10 4
#100000000
0!
0(
#110000000
1!
1&
1(
1-
12
b11 4
#120000000
0!
0(
#130000000
1!
0&
1(
0-
02
b100 4
#140000000
0!
0(
#150000000
1!
1&
1(
1-
12
b101 4
#160000000
0!
0(
#170000000
1!
0&
1(
0-
02
b110 4
#180000000
0!
0(
#190000000
1!
1&
1(
1-
12
b111 4
#200000000
0!
0(
#210000000
1!
1(
b0 4
#220000000
0!
0(
#230000000
1!
0&
1(
0-
02
#240000000
0!
0(
#250000000
1!
1%
1&
1(
1+
1-
1.
12
#260000000
0!
0(
#270000000
1!
1(
#280000000
0!
0(
#290000000
1!
1(
#300000000
0!
0(
#310000000
1!
1(
#320000000
0!
0(
#330000000
1!
1(
#340000000
0!
0(
#350000000
1!
1(
#360000000
0!
1"
0(
1)
1/
#370000000
1!
1(
#380000000
0!
0(
#390000000
1!
1(
#400000000
0!
0"
1#
0(
0)
1*
0/
#410000000
1!
0%
0&
1(
0+
0-
0.
02
#420000000
0!
0(
#430000000
1!
1&
1(
1-
12
b1 4
#440000000
0!
0(
#450000000
1!
0&
1(
0-
02
b10 4
#460000000
0!
0(
#470000000
1!
1&
1(
1-
12
b11 4
#480000000
0!
0(
#490000000
1!
0&
1(
0-
02
b100 4
#500000000
0!
0(
#510000000
1!
1&
1(
1-
12
b101 4
#520000000
0!
0(
#530000000
1!
0&
1(
0-
02
b110 4
#540000000
0!
0(
#550000000
1!
1&
1(
1-
12
b111 4
#560000000
0!
0(
#570000000
1!
1(
b0 4
#580000000
0!
0(
#590000000
1!
0&
1(
0-
02
#600000000
0!
0(
#610000000
1!
1%
1&
1(
1+
1-
1.
12
#620000000
0!
0(
#630000000
1!
0%
0&
1(
0+
0-
0.
02
#640000000
0!
0(
#650000000
1!
1&
1(
1-
12
b1 4
#660000000
0!
0(
#670000000
1!
0&
1(
0-
02
b10 4
#680000000
0!
0(
#690000000
1!
1&
1(
1-
12
b11 4
#700000000
0!
0(
#710000000
1!
0&
1(
0-
02
b100 4
#720000000
0!
1"
0(
1)
1/
#730000000
1!
1&
1(
1-
12
b101 4
#740000000
0!
0(
#750000000
1!
0&
1(
0-
02
b110 4
#760000000
0!
0"
0(
0)
0/
#770000000
1!
1&
1(
1-
12
b111 4
#780000000
0!
0(
#790000000
1!
1(
b0 4
#800000000
0!
0(
#810000000
1!
0&
1(
0-
02
#820000000
0!
0(
#830000000
1!
1%
1&
1(
1+
1-
1.
12
#840000000
0!
0(
#850000000
1!
0%
0&
1(
0+
0-
0.
02
#860000000
0!
0(
#870000000
1!
1&
1(
1-
12
b1 4
#880000000
0!
0(
#890000000
1!
0&
1(
0-
02
b10 4
#900000000
0!
0(
#910000000
1!
1&
1(
1-
12
b11 4
#920000000
0!
0(
#930000000
1!
0&
1(
0-
02
b100 4
#940000000
0!
0(
#950000000
1!
1&
1(
1-
12
b101 4
#960000000
0!
0(
#970000000
1!
0&
1(
0-
02
b110 4
#980000000
0!
0(
#990000000
1!
1&
1(
1-
12
b111 4
#1000000000
0!
0(
#1010000000
1!
1(
b0 4
#1020000000
0!
0(
#1030000000
1!
0&
1(
0-
02
#1040000000
0!
0(
#1050000000
1!
1%
1&
1(
1+
1-
1.
12
#1060000000
0!
0(
#1070000000
1!
0%
0&
1(
0+
0-
0.
02
#1080000000
0!
0(
#1090000000
1!
1&
1(
1-
12
b1 4
#1100000000
0!
0(
#1110000000
1!
0&
1(
0-
02
b10 4
#1120000000
0!
0(
#1130000000
1!
1&
1(
1-
12
b11 4
#1140000000
0!
0(
#1150000000
1!
0&
1(
0-
02
b100 4
#1160000000
0!
0(
#1170000000
1!
1&
1(
1-
12
b101 4
#1180000000
0!
0(
#1190000000
1!
0&
1(
0-
02
b110 4
#1200000000
0!
0(
#1210000000
1!
1&
1(
1-
12
b111 4
#1220000000
0!
0#
0(
0*
#1230000000
1!
1(
b0 4
#1240000000
0!
0(
#1250000000
1!
0&
1(
0-
02
#1260000000
0!
0(
#1270000000
1!
1%
1&
1(
1+
1-
1.
12
#1280000000
0!
0(
#1290000000
1!
1(
#1300000000
0!
0(
#1310000000
1!
1(
#1320000000
0!
0(
#1330000000
1!
1(
#1340000000
0!
0(
#1350000000
1!
1(
#1360000000
0!
0(
#1370000000
1!
1(
#1380000000
0!
0(
#1390000000
1!
1(
#1400000000
0!
0(
#1410000000
1!
1(
#1420000000
0!
0(
#1430000000
1!
1(
#1440000000
0!
0(
#1450000000
1!
1(
#1460000000
0!
0(
#1470000000
1!
1(
#1480000000
0!
0(
#1490000000
1!
1(
#1500000000
0!
0(
#1510000000
1!
1(
#1520000000
0!
1"
b00000000 $
0(
1)
b00000000 ,
1/
b00000000 0
#1530000000
1!
1(
#1540000000
0!
0(
#1550000000
1!
1(
#1560000000
0!
0"
1#
0(
0)
1*
0/
#1570000000
1!
0%
0&
1(
0+
0-
0.
02
#1580000000
0!
0(
#1590000000
1!
1(
b1 4
#1600000000
0!
0(
#1610000000
1!
1(
b10 4
#1620000000
0!
b01111111 $
0(
b01111111 ,
b01111111 0
#1630000000
1!
1&
1(
1-
12
b11 4
#1640000000
0!
0(
#1650000000
1!
1(
b100 4
#1660000000
0!
0(
#1670000000
1!
1(
b101 4
#1680000000
0!
0(
#1690000000
1!
1(
b110 4
#1700000000
0!
0(
#1710000000
1!
1(
b111 4
#1720000000
0!
0(
#1730000000
1!
0&
1(
0-
02
b0 4
#1740000000
0!
0(
#1750000000
1!
1(
#1760000000
0!
0(
#1770000000
1!
1%
1&
1(
1+
1-
1.
12
#1780000000
0!
1'
0(
